[
  {
    "number": "1",
    "title": "Two Sum",
    "slug": "two-sum",
    "difficulty": "Easy",
    "tags": [
      "Array",
      "Hash Table"
    ],
    "language": "Python3",
    "runtime": "3ms (Beats 100%)",
    "memory": "N/A",
    "url": "https://leetcode.com/problems/two-sum/",
    "date": "2026-06-18"
  },
  {
    "number": "3614",
    "title": "Process String with Special Operations II",
    "slug": "process-string-with-special-operations-ii",
    "difficulty": "Hard",
    "tags": [
      "String",
      "Simulation"
    ],
    "language": "Python3",
    "runtime": "0ms",
    "memory": "0.00MB",
    "url": "https://leetcode.com/problems/process-string-with-special-operations-ii/",
    "date": "2026-06-17"
  },
  {
    "number": "1752",
    "title": "Check if Array Is Sorted and Rotated",
    "slug": "check-if-array-is-sorted-and-rotated",
    "difficulty": "Easy",
    "tags": [
      "Array"
    ],
    "language": "Python3",
    "runtime": "20260ms (Beats 100%)",
    "memory": "N/A",
    "url": "https://leetcode.com/problems/check-if-array-is-sorted-and-rotated/",
    "date": "2026-06-18"
  },
  {
    "number": "560",
    "title": "Subarray Sum Equals K",
    "slug": "subarray-sum-equals-k",
    "difficulty": "Medium",
    "tags": [
      "Array",
      "Hash Table",
      "Prefix Sum"
    ],
    "language": "Python3",
    "runtime": "31ms (Beats 77.66%)",
    "memory": "21.74MB (Beats 77.66%)",
    "url": "https://leetcode.com/problems/subarray-sum-equals-k/",
    "date": "2026-06-18"
  },
  {
    "number": "704",
    "title": "Binary Search",
    "slug": "binary-search",
    "difficulty": "Easy",
    "tags": [
      "Array",
      "Binary Search"
    ],
    "language": "Python3",
    "runtime": "0 ms (Beats 100%)",
    "memory": "2MB (Beats 100%)",
    "url": "https://leetcode.com/problems/binary-search/",
    "date": "2026-06-19"
  },
  {
    "number": "35",
    "title": "Search Insert Position",
    "slug": "search-insert-position",
    "difficulty": "Easy",
    "tags": [
      "Array",
      "Binary Search"
    ],
    "language": "Python3",
    "runtime": "0ms (Beats 100%)",
    "memory": "19.85MB (Beats 100%)",
    "url": "https://leetcode.com/problems/search-insert-position/",
    "date": "2026-06-19"
  },
  {
    "number": "33",
    "title": "Search in Rotated Sorted Array",
    "slug": "search-in-rotated-sorted-array",
    "difficulty": "Medium",
    "tags": [
      "Array",
      "Binary Search"
    ],
    "language": "Python3",
    "runtime": "20260ms (Beats 100%)",
    "memory": "N/A",
    "url": "https://leetcode.com/problems/search-in-rotated-sorted-array/",
    "date": "2026-06-19"
  },
  {
    "number": "268",
    "title": "Missing Number",
    "slug": "missing-number",
    "difficulty": "Easy",
    "tags": [
      "Array",
      "Hash Table",
      "Math",
      "Binary Search",
      "Bit Manipulation",
      "Sorting"
    ],
    "language": "Python3",
    "runtime": "0ms (Beats 98%)",
    "memory": "N/A",
    "url": "https://leetcode.com/problems/missing-number/",
    "date": "2026-06-19"
  },
  {
    "number": "4",
    "title": "Median of Two Sorted Arrays",
    "slug": "median-of-two-sorted-arrays",
    "difficulty": "Hard",
    "tags": [
      "Array",
      "Binary Search",
      "Divide and Conquer"
    ],
    "language": "Python3",
    "runtime": "2ms (Beats 100%)",
    "memory": "19.5 MB (Beats 100%)",
    "url": "https://leetcode.com/problems/median-of-two-sorted-arrays/",
    "date": "2026-06-19"
  },
  {
    "number": "88",
    "title": "Merge Sorted Array",
    "slug": "merge-sorted-array",
    "difficulty": "Easy",
    "tags": [
      "Array",
      "Two Pointers",
      "Sorting"
    ],
    "language": "Python3",
    "runtime": "0 ms (Beats 100%)",
    "memory": "N/A",
    "url": "https://leetcode.com/problems/merge-sorted-array/",
    "date": "2026-06-19"
  },
  {
    "number": "39",
    "title": "Combination Sum",
    "slug": "combination-sum",
    "difficulty": "Medium",
    "tags": [
      "Array",
      "Backtracking"
    ],
    "language": "Python3",
    "runtime": "0 ms (Beats 100%)",
    "memory": "N/A",
    "url": "https://leetcode.com/problems/combination-sum/",
    "date": "2026-06-20"
  },
  {
    "number": "509",
    "title": "Fibonacci Number",
    "slug": "fibonacci-number",
    "difficulty": "Easy",
    "tags": [
      "Math",
      "Dynamic Programming",
      "Recursion",
      "Memoization"
    ],
    "language": "Python3",
    "runtime": "0 ms (Beats 100%)",
    "memory": "N/A",
    "url": "https://leetcode.com/problems/fibonacci-number/",
    "date": "2026-06-20"
  },
  {
    "number": "51",
    "title": "N-Queens",
    "slug": "n-queens",
    "difficulty": "Hard",
    "tags": [
      "Array",
      "Backtracking"
    ],
    "language": "Python3",
    "runtime": "010ms (Beats 100%)",
    "memory": "N/A",
    "url": "https://leetcode.com/problems/n-queens/",
    "date": "2026-06-21"
  },
  {
    "number": "876",
    "title": "Middle of the Linked List",
    "slug": "middle-of-the-linked-list",
    "difficulty": "Easy",
    "tags": [
      "Linked List",
      "Two Pointers"
    ],
    "language": "Python3",
    "runtime": "171ms (Beats 95.40%)",
    "memory": "N/A",
    "url": "https://leetcode.com/problems/middle-of-the-linked-list/",
    "date": "2026-06-21"
  },
  {
    "number": "79",
    "title": "Word Search",
    "slug": "word-search",
    "difficulty": "Medium",
    "tags": [
      "Array",
      "String",
      "Backtracking",
      "Depth-First Search",
      "Matrix"
    ],
    "language": "Python3",
    "runtime": "N/A",
    "memory": "N/A",
    "url": "https://leetcode.com/problems/word-search/",
    "date": "2026-06-21"
  },
  {
    "number": "15",
    "title": "3Sum",
    "slug": "3sum",
    "difficulty": "Medium",
    "tags": [
      "Array",
      "Two Pointers",
      "Sorting"
    ],
    "language": "Python3",
    "runtime": "28ms (Beats 100%)",
    "memory": "N/A",
    "url": "https://leetcode.com/problems/3sum/",
    "date": "2026-06-22"
  },
  {
    "number": "1189",
    "title": "Maximum Number of Balloons",
    "slug": "maximum-number-of-balloons",
    "difficulty": "Easy",
    "tags": [
      "Hash Table",
      "String",
      "Counting"
    ],
    "language": "Python3",
    "runtime": "0ms (Beats 100%)",
    "memory": "19.06MB (Beats 100%)",
    "url": "https://leetcode.com/problems/maximum-number-of-balloons/",
    "date": "2026-06-22"
  },
  {
    "number": "144",
    "title": "Binary Tree Preorder Traversal",
    "slug": "binary-tree-preorder-traversal",
    "difficulty": "Easy",
    "tags": [
      "Stack",
      "Tree",
      "Depth-First Search",
      "Binary Tree"
    ],
    "language": "Python3",
    "runtime": "0 ms (Beats 100%)",
    "memory": "0.00MB (Beats 100%)",
    "url": "https://leetcode.com/problems/binary-tree-preorder-traversal/",
    "date": "2026-06-22"
  },
  {
    "number": "102",
    "title": "Binary Tree Level Order Traversal",
    "slug": "binary-tree-level-order-traversal",
    "difficulty": "Medium",
    "tags": [
      "Tree",
      "Breadth-First Search",
      "Binary Tree"
    ],
    "language": "Python3",
    "runtime": "0ms (Beats 100%)",
    "memory": "0.00MB (Beats 100%)",
    "url": "https://leetcode.com/problems/binary-tree-level-order-traversal/",
    "date": "2026-06-22"
  },
  {
    "number": "36",
    "title": "Valid Sudoku",
    "slug": "valid-sudoku",
    "difficulty": "Medium",
    "tags": [
      "Array",
      "Hash Table",
      "Matrix"
    ],
    "language": "Python3",
    "runtime": "0 ms (Beats 96.78%)",
    "memory": "N/A",
    "url": "https://leetcode.com/problems/valid-sudoku/",
    "date": "2026-06-23"
  }
]